setup.py
yGssBn_distributions/Binomialdistribution.py
yGssBn_distributions/Gaussiandistribution.py
yGssBn_distributions/Generaldistribution.py
yGssBn_distributions/__init__.py
yGssBn_distributions.egg-info/PKG-INFO
yGssBn_distributions.egg-info/SOURCES.txt
yGssBn_distributions.egg-info/dependency_links.txt
yGssBn_distributions.egg-info/not-zip-safe
yGssBn_distributions.egg-info/top_level.txt