Metadata-Version: 1.0
Name: yGssBn-distributions
Version: 0.1
Summary: Gaussian & Binomial distributions
Home-page: UNKNOWN
Author: Youssef Saeed
Author-email: y0uss3f071997@gmail.com
License: UNKNOWN
Platform: UNKNOWN
